MANIFEST.in
README.md
setup.py
bin/moneywagon
moneywagon/__init__.py
moneywagon/arbitrage.py
moneywagon/bip38.py
moneywagon/blocktime_adjustments.py
moneywagon/core.py
moneywagon/crypto_data.py
moneywagon/crypto_data_extractor.py
moneywagon/currency_support.py
moneywagon/decomissioned_services.py
moneywagon/historical_price.py
moneywagon/mcaf.py
moneywagon/network_replay.py
moneywagon/onchain_exchange.py
moneywagon/superthin.py
moneywagon/supply_estimator.py
moneywagon/tx.py
moneywagon/wallet.py
moneywagon.egg-info/PKG-INFO
moneywagon.egg-info/SOURCES.txt
moneywagon.egg-info/dependency_links.txt
moneywagon.egg-info/requires.txt
moneywagon.egg-info/top_level.txt
moneywagon/services/__init__.py
moneywagon/services/blockchain_services.py
moneywagon/services/exchange_services.py