Metadata-Version: 1.1
Name: moneywagon
Version: 1.22.1
Summary: Next Generation Cryptocurrency Platform
Home-page: https://github.com/priestc/moneywagon
Author: Chris Priest
Author-email: cp368202@ohiou.edu
License: LICENSE
Platform: UNKNOWN
Classifier: Development Status :: 5 - Production/Stable
Classifier: Programming Language :: Python
Classifier: Programming Language :: Python :: 2.7
Classifier: Programming Language :: Python :: 3
